keinsum/__init__.py
keinsum-0.4.dist-info/METADATA
keinsum-0.4.dist-info/WHEEL
keinsum-0.4.dist-info/top_level.txt
keinsum-0.4.dist-info/RECORD
