Metadata-Version: 2.1
Name: keinsum
Version: 0.4
Summary: An extension of np.einsum where capital letters serve as multiple ellipses.
Home-page: https://github.com/axil/keinsum
Author: Lev Maximov
Author-email: lev.maximov@gmail.com
License: MIT License
Keywords: einsum,array,ndarray,numpy,contraction
Platform: UNKNOWN
Classifier: Development Status :: 4 - Beta
Classifier: License :: OSI Approved :: MIT License
Classifier: Operating System :: OS Independent
Classifier: Programming Language :: Python :: 3.7
Classifier: Programming Language :: Python :: 3.8
Classifier: Programming Language :: Python :: 3.9
Classifier: Programming Language :: Python :: 3.10
Classifier: Programming Language :: Python :: 3.11
Requires-Python: >=3.7
Requires-Dist: numpy
